README.txt
setup.cfg
setup.py
silvainstall/__init__.py
silvainstall/main.py
silvainstall.egg-info/PKG-INFO
silvainstall.egg-info/SOURCES.txt
silvainstall.egg-info/dependency_links.txt
silvainstall.egg-info/entry_points.txt
silvainstall.egg-info/not-zip-safe
silvainstall.egg-info/requires.txt
silvainstall.egg-info/top_level.txt
