Metadata-Version: 1.0
Name: silvainstall
Version: 0.1dev-r23357
Summary: A script that lets you quickly set up a Zope instance in which you can use standard Python tools like easy_install to add packages
Home-page: http://cheeseshop.python.org/pypi/silvainstall
Author: Infrae
Author-email: silva-dev@infrae.com
License: UNKNOWN
Keywords: plone zope content management cms
Platform: UNKNOWN
Classifier: Framework :: Zope2
